Metadata-Version: 2.1
Name: mycroft-plugin-rhvoice
Version: 1.0.0
Summary: RHVoice TTS plugin for Mycroft
Home-page: https://github.com/putnik/mycroft-plugin-rhvoice
Author: Sergey Leschina
Author-email: mail@putnik.tech
License: Apache-2.0
Keywords: mycroft plugin tts rhvoice
Platform: UNKNOWN
Classifier: Development Status :: 3 - Alpha
Classifier: Intended Audience :: Developers
Classifier: License :: OSI Approved :: Apache Software License
Classifier: Topic :: Text Processing :: Linguistic
Classifier: Natural Language :: Russian
Classifier: Programming Language :: Python :: 3
Classifier: Programming Language :: Python :: 3.7
Classifier: Programming Language :: Python :: 3.8
Classifier: Programming Language :: Python :: 3.9
